fourier_core.cpython-311-x86_64-linux-gnu.so
fourier_core.pyi
fourier_core-0.2.5a1.dist-info/METADATA
fourier_core-0.2.5a1.dist-info/WHEEL
fourier_core-0.2.5a1.dist-info/top_level.txt
fourier_core-0.2.5a1.dist-info/RECORD
