Metadata-Version: 2.1
Name: fourier-core
Version: 0.2.5a1
Summary: Robotics Control System for the All Robotics
Author-email: "Fourier Intelligence Ltd." <rcs@fftai.com>, Xin Chen <xin.chen@fftai.com>, Yuxiang Gao <yuxiang.gao@fftai.com>
Classifier: Development Status :: 3 - Alpha
Classifier: Intended Audience :: Developers
Classifier: Programming Language :: Python :: 3.11
Requires-Python: ==3.11.*
Requires-Dist: numpy<2.0.0,>=1.26.4
Requires-Dist: pyserial==3.5
Requires-Dist: pyyaml>=6.0.1
Requires-Dist: rich>=13.7.1
Requires-Dist: typer>=0.12.3
Requires-Dist: msgpack>=1.0.8
Requires-Dist: msgpack-numpy>=0.4.8
Requires-Dist: eclipse-zenoh==0.11.0
Requires-Dist: loguru>=0.7.2
Requires-Dist: inputs>=0.5
Requires-Dist: torch>=2.3.0
Provides-Extra: all
Requires-Dist: fourier-core[rl]; extra == "all"
Provides-Extra: docs
Requires-Dist: mkdocs>=1.6.0; extra == "docs"
Requires-Dist: mkdocs-material>=9.5.24; extra == "docs"
Requires-Dist: mkdocstrings[python]>=0.25.1; extra == "docs"
Requires-Dist: mkdocs-gen-files>=0.5.0; extra == "docs"
Requires-Dist: mkdocs-literate-nav>=0.6.1; extra == "docs"
Requires-Dist: mkdocs-section-index>=0.3.9; extra == "docs"
Provides-Extra: rl
Requires-Dist: torch>=2.3.0; extra == "rl"
